quicketl/__init__.py
quicketl/_version.py
quicketl/py.typed
quicketl/cli/__init__.py
quicketl/cli/info.py
quicketl/cli/init.py
quicketl/cli/main.py
quicketl/cli/run.py
quicketl/cli/schema.py
quicketl/cli/validate.py
quicketl/cli/workflow.py
quicketl/config/__init__.py
quicketl/config/checks.py
quicketl/config/environments.py
quicketl/config/loader.py
quicketl/config/models.py
quicketl/config/profiles.py
quicketl/config/project.py
quicketl/config/transforms.py
quicketl/config/workflow.py
quicketl/engines/__init__.py
quicketl/engines/backends.py
quicketl/engines/base.py
quicketl/engines/expressions.py
quicketl/integrations/__init__.py
quicketl/integrations/airflow.py
quicketl/io/__init__.py
quicketl/io/readers/__init__.py
quicketl/io/readers/database.py
quicketl/io/readers/file.py
quicketl/io/writers/__init__.py
quicketl/io/writers/database.py
quicketl/io/writers/file.py
quicketl/logging/__init__.py
quicketl/logging/setup.py
quicketl/pipeline/__init__.py
quicketl/pipeline/context.py
quicketl/pipeline/pipeline.py
quicketl/pipeline/result.py
quicketl/quality/__init__.py
quicketl/quality/checks.py
quicketl/quality/runner.py
quicketl/quality/contracts/__init__.py
quicketl/quality/contracts/pandera_adapter.py
quicketl/quality/contracts/registry.py
quicketl/quality/contracts/schema.py
quicketl/secrets/__init__.py
quicketl/secrets/aws.py
quicketl/secrets/azure.py
quicketl/secrets/base.py
quicketl/secrets/env.py
quicketl/secrets/registry.py
quicketl/sinks/__init__.py
quicketl/sinks/vector/__init__.py
quicketl/sinks/vector/base.py
quicketl/sinks/vector/pgvector.py
quicketl/sinks/vector/pinecone.py
quicketl/sinks/vector/qdrant.py
quicketl/telemetry/__init__.py
quicketl/telemetry/context.py
quicketl/telemetry/openlineage.py
quicketl/telemetry/opentelemetry.py
quicketl/transforms/__init__.py
quicketl/transforms/ai/__init__.py
quicketl/transforms/ai/chunk.py
quicketl/transforms/ai/embed.py
quicketl/transforms/ai/strategies.py
quicketl/transforms/ai/providers/__init__.py
quicketl-1.5.0.dist-info/METADATA
quicketl-1.5.0.dist-info/WHEEL
quicketl-1.5.0.dist-info/entry_points.txt
quicketl-1.5.0.dist-info/licenses/LICENSE
quicketl-1.5.0.dist-info/RECORD
