Metadata-Version: 2.4
Name: quicketl
Version: 1.5.0
Summary: QuickETL - Fast & Flexible Python ETL Framework with 20+ backend support via Ibis
Project-URL: Homepage, https://quicketl.com
Project-URL: Documentation, https://quicketl.com
Project-URL: Repository, https://github.com/ameijin/quicketl
Project-URL: Issues, https://github.com/ameijin/quicketl/issues
Author-email: Eiji <eiji@eidosoft.co>
License: MIT
License-File: LICENSE
Keywords: data-engineering,duckdb,elt,etl,ibis,pipeline,polars,quicketl
Classifier: Development Status :: 3 - Alpha
Classifier: Intended Audience :: Developers
Classifier: License :: OSI Approved :: MIT License
Classifier: Programming Language :: Python :: 3
Classifier: Programming Language :: Python :: 3.12
Classifier: Programming Language :: Python :: 3.13
Classifier: Topic :: Database
Classifier: Topic :: Scientific/Engineering
Classifier: Typing :: Typed
Requires-Python: >=3.12
Requires-Dist: fsspec>=2024.6
Requires-Dist: ibis-framework[duckdb,polars]>=9.0
Requires-Dist: pydantic>=2.10
Requires-Dist: pyyaml>=6.0
Requires-Dist: rich>=13.0
Requires-Dist: structlog>=24.0
Requires-Dist: typer>=0.12
Provides-Extra: ai
Requires-Dist: nltk>=3.8; extra == 'ai'
Requires-Dist: openai>=1.0; extra == 'ai'
Requires-Dist: pgvector>=0.2; extra == 'ai'
Requires-Dist: pinecone-client>=3.0; extra == 'ai'
Requires-Dist: psycopg2-binary>=2.9; extra == 'ai'
Requires-Dist: qdrant-client>=1.7; extra == 'ai'
Requires-Dist: sentence-transformers>=2.2; extra == 'ai'
Requires-Dist: tiktoken>=0.5; extra == 'ai'
Provides-Extra: all
Requires-Dist: adlfs>=2024.4; extra == 'all'
Requires-Dist: azure-identity>=1.15; extra == 'all'
Requires-Dist: azure-keyvault-secrets>=4.8; extra == 'all'
Requires-Dist: azure-storage-blob>=12.19; extra == 'all'
Requires-Dist: boto3>=1.34; extra == 'all'
Requires-Dist: gcsfs>=2024.6; extra == 'all'
Requires-Dist: google-cloud-storage>=2.14; extra == 'all'
Requires-Dist: hypothesis>=6.100; extra == 'all'
Requires-Dist: ibis-framework[bigquery]>=9.0; extra == 'all'
Requires-Dist: ibis-framework[clickhouse]>=9.0; extra == 'all'
Requires-Dist: ibis-framework[datafusion]>=9.0; extra == 'all'
Requires-Dist: ibis-framework[mysql]>=9.0; extra == 'all'
Requires-Dist: ibis-framework[postgres]>=9.0; extra == 'all'
Requires-Dist: ibis-framework[pyspark]>=9.0; extra == 'all'
Requires-Dist: ibis-framework[snowflake]>=9.0; extra == 'all'
Requires-Dist: ibis-framework[trino]>=9.0; extra == 'all'
Requires-Dist: mkdocs-gen-files>=0.5; extra == 'all'
Requires-Dist: mkdocs-literate-nav>=0.6; extra == 'all'
Requires-Dist: mkdocs-material>=9.5; extra == 'all'
Requires-Dist: mkdocs-section-index>=0.3; extra == 'all'
Requires-Dist: mkdocs>=1.6; extra == 'all'
Requires-Dist: mkdocstrings[python]>=0.25; extra == 'all'
Requires-Dist: moto>=5.0; extra == 'all'
Requires-Dist: mypy>=1.10; extra == 'all'
Requires-Dist: nltk>=3.8; extra == 'all'
Requires-Dist: openai>=1.0; extra == 'all'
Requires-Dist: openlineage-python>=1.8; extra == 'all'
Requires-Dist: opentelemetry-api>=1.22; extra == 'all'
Requires-Dist: opentelemetry-exporter-otlp>=1.22; extra == 'all'
Requires-Dist: opentelemetry-sdk>=1.22; extra == 'all'
Requires-Dist: pandas>=2.0; extra == 'all'
Requires-Dist: pandera[polars]>=0.20; extra == 'all'
Requires-Dist: pgvector>=0.2; extra == 'all'
Requires-Dist: pinecone-client>=3.0; extra == 'all'
Requires-Dist: pre-commit>=3.7; extra == 'all'
Requires-Dist: psycopg2-binary>=2.9; extra == 'all'
Requires-Dist: pymdown-extensions>=10.0; extra == 'all'
Requires-Dist: pytest-asyncio>=0.23; extra == 'all'
Requires-Dist: pytest-benchmark>=4.0; extra == 'all'
Requires-Dist: pytest-cov>=5.0; extra == 'all'
Requires-Dist: pytest-mock>=3.12; extra == 'all'
Requires-Dist: pytest>=8.0; extra == 'all'
Requires-Dist: qdrant-client>=1.7; extra == 'all'
Requires-Dist: responses>=0.25; extra == 'all'
Requires-Dist: ruff>=0.5; extra == 'all'
Requires-Dist: s3fs>=2024.6; extra == 'all'
Requires-Dist: sentence-transformers>=2.2; extra == 'all'
Requires-Dist: setuptools>=60.0; extra == 'all'
Requires-Dist: tiktoken>=0.5; extra == 'all'
Provides-Extra: aws
Requires-Dist: boto3>=1.34; extra == 'aws'
Requires-Dist: s3fs>=2024.6; extra == 'aws'
Provides-Extra: azure
Requires-Dist: adlfs>=2024.4; extra == 'azure'
Requires-Dist: azure-storage-blob>=12.19; extra == 'azure'
Provides-Extra: bigquery
Requires-Dist: ibis-framework[bigquery]>=9.0; extra == 'bigquery'
Provides-Extra: chunking
Requires-Dist: nltk>=3.8; extra == 'chunking'
Requires-Dist: tiktoken>=0.5; extra == 'chunking'
Provides-Extra: clickhouse
Requires-Dist: ibis-framework[clickhouse]>=9.0; extra == 'clickhouse'
Provides-Extra: contracts
Requires-Dist: pandera[polars]>=0.20; extra == 'contracts'
Provides-Extra: datafusion
Requires-Dist: ibis-framework[datafusion]>=9.0; extra == 'datafusion'
Provides-Extra: dev
Requires-Dist: hypothesis>=6.100; extra == 'dev'
Requires-Dist: moto>=5.0; extra == 'dev'
Requires-Dist: mypy>=1.10; extra == 'dev'
Requires-Dist: pre-commit>=3.7; extra == 'dev'
Requires-Dist: pytest-asyncio>=0.23; extra == 'dev'
Requires-Dist: pytest-benchmark>=4.0; extra == 'dev'
Requires-Dist: pytest-cov>=5.0; extra == 'dev'
Requires-Dist: pytest-mock>=3.12; extra == 'dev'
Requires-Dist: pytest>=8.0; extra == 'dev'
Requires-Dist: responses>=0.25; extra == 'dev'
Requires-Dist: ruff>=0.5; extra == 'dev'
Provides-Extra: docs
Requires-Dist: mkdocs-gen-files>=0.5; extra == 'docs'
Requires-Dist: mkdocs-literate-nav>=0.6; extra == 'docs'
Requires-Dist: mkdocs-material>=9.5; extra == 'docs'
Requires-Dist: mkdocs-section-index>=0.3; extra == 'docs'
Requires-Dist: mkdocs>=1.6; extra == 'docs'
Requires-Dist: mkdocstrings[python]>=0.25; extra == 'docs'
Requires-Dist: pymdown-extensions>=10.0; extra == 'docs'
Provides-Extra: embeddings-huggingface
Requires-Dist: sentence-transformers>=2.2; extra == 'embeddings-huggingface'
Provides-Extra: embeddings-openai
Requires-Dist: openai>=1.0; extra == 'embeddings-openai'
Requires-Dist: tiktoken>=0.5; extra == 'embeddings-openai'
Provides-Extra: enterprise
Requires-Dist: azure-identity>=1.15; extra == 'enterprise'
Requires-Dist: azure-keyvault-secrets>=4.8; extra == 'enterprise'
Requires-Dist: boto3>=1.34; extra == 'enterprise'
Requires-Dist: openlineage-python>=1.8; extra == 'enterprise'
Requires-Dist: opentelemetry-api>=1.22; extra == 'enterprise'
Requires-Dist: opentelemetry-exporter-otlp>=1.22; extra == 'enterprise'
Requires-Dist: opentelemetry-sdk>=1.22; extra == 'enterprise'
Provides-Extra: gcp
Requires-Dist: gcsfs>=2024.6; extra == 'gcp'
Requires-Dist: google-cloud-storage>=2.14; extra == 'gcp'
Provides-Extra: mysql
Requires-Dist: ibis-framework[mysql]>=9.0; extra == 'mysql'
Provides-Extra: openlineage
Requires-Dist: openlineage-python>=1.8; extra == 'openlineage'
Provides-Extra: opentelemetry
Requires-Dist: opentelemetry-api>=1.22; extra == 'opentelemetry'
Requires-Dist: opentelemetry-exporter-otlp>=1.22; extra == 'opentelemetry'
Requires-Dist: opentelemetry-sdk>=1.22; extra == 'opentelemetry'
Provides-Extra: pandas
Requires-Dist: pandas>=2.0; extra == 'pandas'
Provides-Extra: postgres
Requires-Dist: ibis-framework[postgres]>=9.0; extra == 'postgres'
Provides-Extra: quality
Requires-Dist: pandera[polars]>=0.20; extra == 'quality'
Provides-Extra: secrets-aws
Requires-Dist: boto3>=1.34; extra == 'secrets-aws'
Provides-Extra: secrets-azure
Requires-Dist: azure-identity>=1.15; extra == 'secrets-azure'
Requires-Dist: azure-keyvault-secrets>=4.8; extra == 'secrets-azure'
Provides-Extra: snowflake
Requires-Dist: ibis-framework[snowflake]>=9.0; extra == 'snowflake'
Provides-Extra: spark
Requires-Dist: ibis-framework[pyspark]>=9.0; extra == 'spark'
Requires-Dist: setuptools>=60.0; extra == 'spark'
Provides-Extra: trino
Requires-Dist: ibis-framework[trino]>=9.0; extra == 'trino'
Provides-Extra: vector-pgvector
Requires-Dist: pgvector>=0.2; extra == 'vector-pgvector'
Requires-Dist: psycopg2-binary>=2.9; extra == 'vector-pgvector'
Provides-Extra: vector-pinecone
Requires-Dist: pinecone-client>=3.0; extra == 'vector-pinecone'
Provides-Extra: vector-qdrant
Requires-Dist: qdrant-client>=1.7; extra == 'vector-qdrant'
